aiflow/__init__.py
aiflow/hooks/__init__.py
aiflow/hooks/elastic_hook.py
aiflow/hooks/mongo_hook.py
aiflow/operators/__init__.py
aiflow/operators/elastic_operator.py
aiflow/operators/mongo_operator.py
aiflow/operators/regex_operator.py
aiflow/operators/text_classification_operator.py
aiflow/units/__init__.py
aiflow/units/doc2mat_unit.py
aiflow/units/doc2vec_unit.py
aiflow-1.0.0.dist-info/LICENSE
aiflow-1.0.0.dist-info/METADATA
aiflow-1.0.0.dist-info/WHEEL
aiflow-1.0.0.dist-info/top_level.txt
aiflow-1.0.0.dist-info/RECORD
