Metadata-Version: 2.1
Name: aiflow
Version: 1.0.0
Summary: AI Flow, an extend operators library for airflow, which helps AI engineer to write less, reuse more, integrate easily.
Home-page: https://github.com/Marcnuth/aiflow
Author: Xianxian Huang
Author-email: hxianxian@gmail.com
License: Apache License 2.0
Platform: UNKNOWN
Classifier: Topic :: Scientific/Engineering :: Artificial Intelligence
Classifier: Topic :: Software Development :: Libraries
Classifier: Programming Language :: Python :: 3
Requires-Dist: apache-airflow
Requires-Dist: pymongo
Requires-Dist: pathlib
Requires-Dist: jsonpath
Requires-Dist: pandas
Requires-Dist: numpy
Requires-Dist: gensim
Requires-Dist: nltk
Requires-Dist: elasticsearch (<7.0.0,>=6.0.0)
